{
  "display": {
    "title": "Unbreakable",
    "description": "You have crafted the four obsidian tools",
    "icon": {
      "item": "mores:obsidian_axe"
    },
    "background": "minecraft:textures/gui/advancements/backgrounds/stone.png",
    "frame": "task",
    "announce_to_chat": true,
    "hidden": false
  },
  "parent": "minecraft:story/form_obsidian",
  "criteria": {
    "obtain_copper_ore": {
      "trigger": "minecraft:inventory_changed",
      "conditions": {
        "items": [
          {
            "item": "mores:obsidian_sword"
          },
          {
            "item": "mores:obsidian_pickaxe"
          },
          {
            "item": "mores:obsidian_axe"
          },
          {
            "item": "mores:obsidian_shovel"
          }
        ]
      }
    }
  },
  "rewards": {
    "experience": 75
  }
}