{
  "display": {
    "title": "Is This Diamond?",
    "description": "You have mined your very first silver ore",
    "icon": {
      "item": "mores:silver_ore"
    },
    "background": "minecraft:textures/gui/advancements/backgrounds/stone.png",
    "frame": "task",
    "announce_to_chat": true,
    "hidden": false
  },
  "parent": "mores:mores/mores",
  "criteria": {
    "obtain_copper_ore": {
      "trigger": "minecraft:inventory_changed",
      "conditions": {
        "items": [
          {
            "item": "mores:silver_ore",
            "data": 0
          }
        ]
      }
    }
  },
  "rewards": {
    "experience": 20
  }
}