{
  "display": {
    "title": "Immovable",
    "description": "Craft full obsidian armor",
    "icon": {
      "item": "mores:obsidian_chestplate"
    },
    "background": "minecraft:textures/gui/advancements/backgrounds/stone.png",
    "frame": "task",
    "announce_to_chat": true,
    "hidden": false
  },
  "parent": "mores:craft_obsidian_tools",
  "criteria": {
    "craft_full_obsidian_armor": {
      "trigger": "minecraft:inventory_changed",
      "conditions": {
        "items": [
          {
            "items": [
              "mores:obsidian_helmet"
            ]
          },
          {
            "items": [
              "mores:obsidian_chestplate"
            ]
          },
          {
            "items": [
              "mores:obsidian_leggings"
            ]
          },
          {
            "items": [
              "mores:obsidian_boots"
            ]
          }
        ]
      }
    }
  },
  "rewards": {
    "experience": 150
  }
}