{
  "display": {
    "title": "Just Because I Can",
    "description": "Craft full chainmail armor",
    "icon": {
      "item": "minecraft:chainmail_chestplate"
    },
    "background": "minecraft:textures/gui/advancements/backgrounds/stone.png",
    "frame": "task",
    "announce_to_chat": true,
    "hidden": false
  },
  "parent": "mores:craft_chain",
  "criteria": {
    "craft_full_chainmail": {
      "trigger": "minecraft:inventory_changed",
      "conditions": {
        "items": [
          {
            "items": [
              "minecraft:chainmail_helmet"
            ]
          },
          {
            "items": [
              "minecraft:chainmail_chestplate"
            ]
          },
          {
            "items": [
              "minecraft:chainmail_leggings"
            ]
          },
          {
            "items": [
              "minecraft:chainmail_boots"
            ]
          }
        ]
      }
    }
  },
  "rewards": {
    "experience": 100
  }
}