{
  "display": {
    "title": "The Dark Knight",
    "description": "Craft full onyx armor",
    "icon": {
      "item": "mores:onyx_helmet"
    },
    "background": "minecraft:textures/gui/advancements/backgrounds/stone.png",
    "frame": "task",
    "announce_to_chat": true,
    "hidden": false
  },
  "parent": "mores:obtain_onyx",
  "criteria": {
    "obtain_onyx_armor": {
      "trigger": "minecraft:inventory_changed",
      "conditions": {
        "items": [
          {
            "items": [
              "mores:onyx_helmet"
            ]
          },
          {
            "items": [
              "mores:onyx_chestplate"
            ]
          },
          {
            "items": [
              "mores:onyx_leggings"
            ]
          },
          {
            "items": [
              "mores:onyx_boots"
            ]
          }
        ]
      }
    }
  },
  "rewards": {
    "experience": 400
  }
}