{
  "display": {
    "title": "Look at my horse",
    "description": "My horse is amazing! - Craft horse armor",
    "icon": {
      "item": "mores:tin_horse_armor"
    },
    "background": "minecraft:textures/gui/advancements/backgrounds/stone.png",
    "frame": "task",
    "announce_to_chat": true,
    "hidden": false
  },
  "parent": "mores:smelt_more",
  "criteria": {
    "craft_horse_armor": {
      "trigger": "minecraft:inventory_changed",
      "conditions": {
        "items": [
          {
            "items": [
              "mores:silver_horse_armor",
              "mores:tanzanite_horse_armor",
              "mores:copper_horse_armor",
              "mores:tin_horse_armor",
              "mores:cobalt_horse_armor",
              "mores:emerald_horse_armor",
              "mores:obsidian_horse_armor",
              "mores:bronze_horse_armor",
              "mores:steel_horse_armor",
              "minecraft:golden_horse_armor",
              "minecraft:iron_horse_armor",
              "minecraft:diamond_horse_armor",
              "mores:amethyst_horse_armor",
              "mores:topaz_horse_armor",
              "mores:tourmaline_horse_armor",
              "mores:onyx_horse_armor",
              "mores:ruby_horse_armor",
              "mores:sapphire_horse_armor",
              "mores:turquoise_horse_armor",
              "mores:moissanite_horse_armor",
              "mores:graphene_horse_armor",
              "mores:sterling_horse_armor",
              "mores:netherite_horse_armor"
          ]
        }
      ]
    }
  }
},
  "requirements": [
    ["craft_horse_armor"]
  ],
  "rewards": {
    "experience": 100,
    "function" : "mores:mores/play_my_horse"
  }
}